<?xml version='1.0' encoding='utf-8' standalone='yes' ?>
<map>
    
    <string name="8">영어 듣기 평가 (1학년)</string>
    <string name="8_Day">화</string>
	
    <string name="9">영어 듣기 평가 (2학년)</string>
    <string name="9_Day">수</string>
	
    <string name="10">영어 듣기 평가 (3학년)</string>
    <string name="10_Day">목</string>
    
    <string name="11">교과 체험 학습</string>
    <string name="11_Day">금</string>
    
    <string name="23">양원철 왕자님 생일</string>
    <string name="23_Day">수</string>
	
    <string name="30">1학기 중간고사</string>
    <string name="30_Day">수</string>
	
    <int name="days" value="30" />
</map>
